LICENSE
alembic/README
alembic/alembic.ini
alembic/env.py
alembic/script.py.mako
alembic/versions/25527d692d46_resize_meta_value_column.py
alembic/versions/709085f65102_added_rulesets.py
alembic/versions/892f53ea8054_init.py
resources/config.toml
yaramanager/__init__.py
yaramanager/commands/__init__.py
yaramanager/commands/add.py
yaramanager/commands/cli.py
yaramanager/commands/config.py
yaramanager/commands/db.py
yaramanager/commands/delete.py
yaramanager/commands/edit.py
yaramanager/commands/export.py
yaramanager/commands/get.py
yaramanager/commands/list.py
yaramanager/commands/new.py
yaramanager/commands/parse.py
yaramanager/commands/read.py
yaramanager/commands/ruleset.py
yaramanager/commands/scan.py
yaramanager/commands/search.py
yaramanager/commands/stats.py
yaramanager/commands/tags.py
yaramanager/commands/version.py
yaramanager/config.py
yaramanager/db/__init__.py
yaramanager/db/base.py
yaramanager/db/base_class.py
yaramanager/db/session.py
yaramanager/main.py
yaramanager/models/__init__.py
yaramanager/models/meta.py
yaramanager/models/rule.py
yaramanager/models/ruleset.py
yaramanager/models/string.py
yaramanager/models/tables.py
yaramanager/models/tag.py
yaramanager/models/yarabuilder.py
yaramanager/utils/__init__.py
yaramanager/utils/output.py
yaramanager/utils/platform.py
yaramanager/utils/utils.py
yaramanager-0.2.1.dist-info/entry_points.txt
yaramanager-0.2.1.dist-info/LICENSE
yaramanager-0.2.1.dist-info/WHEEL
yaramanager-0.2.1.dist-info/METADATA
yaramanager-0.2.1.dist-info/RECORD
