Metadata-Version: 2.1
Name: yaramanager
Version: 0.2.1
Summary: CLI tool to manage your yara rules
Home-page: https://github.com/3c7/yaramanager
License: MIT
Keywords: yara,rule,manage
Author: 3c7
Author-email: 3c7@posteo.de
Requires-Python: >=3.8,<3.11
Classifier: Development Status :: 3 - Alpha
Classifier: Environment :: Console
Classifier: Intended Audience :: Information Technology
Classifier: Intended Audience :: Science/Research
Classifier: Intended Audience :: System Administrators
Classifier: License :: OSI Approved :: MIT License
Classifier: Operating System :: OS Independent
Classifier: Programming Language :: Python :: 3
Classifier: Programming Language :: Python :: 3.8
Classifier: Programming Language :: Python :: 3.9
Classifier: Programming Language :: Python :: 3.10
Classifier: Programming Language :: Python :: 3
Classifier: Programming Language :: Python :: 3 :: Only
Classifier: Programming Language :: Python :: 3.7
Classifier: Programming Language :: Python :: 3.8
Classifier: Programming Language :: Python :: 3.9
Classifier: Topic :: Security
Classifier: Topic :: Utilities
Provides-Extra: mysql
Provides-Extra: pgsql
Requires-Dist: PyMySQL (>=1.0.2,<2.0.0); extra == "mysql"
Requires-Dist: SQLAlchemy (>=1.4.2,<2.0.0)
Requires-Dist: alembic (>=1.5.8,<2.0.0)
Requires-Dist: click (>=8.0.4,<9.0.0)
Requires-Dist: plyara (>=2.1.1,<3.0.0)
Requires-Dist: psycopg2 (>=2.9.3,<3.0.0); extra == "pgsql"
Requires-Dist: requests (>=2.25.1,<3.0.0)
Requires-Dist: rich (>=11.2.0,<12.0.0)
Requires-Dist: toml (>=0.10.2,<0.11.0)
Requires-Dist: yara-python (>=4.1.3,<5.0.0)
Requires-Dist: yarabuilder (>=0.0.6,<0.0.7)
Project-URL: Repository, https://github.com/3c7/yaramanager
